Metadata-Version: 2.1
Name: gallerize
Version: 0.4
Summary: Create a static HTML/CSS image gallery from a bunch of images.
Home-page: https://homework.nwsnet.de/releases/cc0e/#gallerize
Author: Jochen Kupperschmidt
Author-email: homework@nwsnet.de
License: MIT
Keywords: gallery
Platform: any
Classifier: Environment :: Console
Classifier: License :: OSI Approved :: MIT License
Classifier: Natural Language :: English
Classifier: Operating System :: OS Independent
Classifier: Programming Language :: Python
Classifier: Programming Language :: Python :: 3
Classifier: Programming Language :: Python :: 3.7
Classifier: Programming Language :: Python :: 3.8
Classifier: Programming Language :: Python :: 3.9
Classifier: Topic :: Communications :: File Sharing
Classifier: Topic :: Internet :: WWW/HTTP
Classifier: Topic :: Multimedia :: Graphics :: Presentation
Requires-Python: >=3.7
